MANIFEST.in
README
setup.py
django_facebook_helper/__init__.py
django_facebook_helper/admin.py
django_facebook_helper/backends.py
django_facebook_helper/decorators.py
django_facebook_helper/forms.py
django_facebook_helper/middleware.py
django_facebook_helper/models.py
django_facebook_helper/tests.py
django_facebook_helper/urls.py
django_facebook_helper/views.py
django_facebook_helper.egg-info/PKG-INFO
django_facebook_helper.egg-info/SOURCES.txt
django_facebook_helper.egg-info/dependency_links.txt
django_facebook_helper.egg-info/top_level.txt
django_facebook_helper/templates/dfh_splash_screen.html
django_facebook_helper/templates/facebook-redirect.html
django_facebook_helper/templates/friends.html
django_facebook_helper/templates/wall-post.html
django_facebook_helper/templatetags/__init__.py
django_facebook_helper/templatetags/__init__.pyc
django_facebook_helper/templatetags/django_facebook_helper_tags.py
django_facebook_helper/templatetags/django_facebook_helper_tags.pyc
tests/__init__.py