Metadata-Version: 1.1
Name: django-facebook-helper
Version: 0.3.7
Summary: A Django application for helping in facebook login an managing.
Home-page: http://packages.python.org/django_facebook_helper
Author: Samuel Barrado
Author-email: samuel.barrado@gmail.com
License: BSD
Keywords: django facebook
Platform: UNKNOWN
Classifier: Development Status :: 3 - Alpha
Classifier: Topic :: Utilities
Classifier: License :: OSI Approved :: BSD License
